[{
  "_id": {
    "$oid": "68660ef56fd728291e7ef8c1"
  },
  "userId": {
    "$oid": "68660ef56fd728291e7ef8be"
  },
  "coins": 3000,
  "decorations": [
    {
      "decorId": {
        "$oid": "68660edaf079d0ff8d6cc86d"
      },
      "placed": false,
      "position": [
        -19.53682049560269,
        0,
        22.512656410474086
      ],
      "rotation": [
        -3.141592653589793,
        1.2246467991473532e-16,
        -3.141592653589793
      ],
      "_id": {
        "$oid": "688d9a4d715eb2233c8cb119"
      }
    },
    {
      "decorId": {
        "$oid": "68660edaf079d0ff8d6cc86e"
      },
      "placed": true,
      "position": [
        16.910230375489363,
        0,
        -12.386936459911055
      ],
      "rotation": [
        -3.141592653589793,
        1.2246467991473532e-16,
        -3.141592653589793
      ],
      "_id": {
        "$oid": "688d9a4d715eb2233c8cb11a"
      }
    },
    {
      "decorId": {
        "$oid": "68660edaf079d0ff8d6cc86f"
      },
      "placed": true,
      "position": [
        -20.037430872264203,
        0,
        -13.082617295232005
      ],
      "rotation": [
        0,
        0,
        0
      ],
      "_id": {
        "$oid": "688d9b6540cda3e766bab2fa"
      }
    },
    {
      "decorId": {
        "$oid": "688d775f0a520a3cbc136fa7"
      },
      "placed": true,
      "position": [
        20.77764023571838,
        0,
        17.202673002276747
      ],
      "rotation": [
        0,
        -1.5707963267948966,
        0
      ],
      "_id": {
        "$oid": "688d9b6840cda3e766bab312"
      }
    },
    {
      "decorId": {
        "$oid": "688d5c240a520a3cbc136fa3"
      },
      "placed": true,
      "position": [
        21.597377729590917,
        8.5,
        21.811140667244395
      ],
      "rotation": [
        0,
        -1.5707963267948966,
        0
      ],
      "_id": {
        "$oid": "688d9b7140cda3e766bab330"
      }
    },
    {
      "decorId": {
        "$oid": "688d676d0a520a3cbc136fa6"
      },
      "placed": false,
      "position": [
        0,
        0,
        0
      ],
      "rotation": [
        0,
        0,
        0
      ],
      "_id": {
        "$oid": "688d9b9140cda3e766bab35c"
      }
    },
    {
      "decorId": {
        "$oid": "688d60610a520a3cbc136fa5"
      },
      "placed": true,
      "position": [
        -6.897983291313196,
        0,
        -21.7040398060115
      ],
      "rotation": [
        0,
        0,
        0
      ],
      "_id": {
        "$oid": "688d9b9240cda3e766bab386"
      }
    },
    {
      "decorId": {
        "$oid": "68660edaf079d0ff8d6cc871"
      },
      "placed": true,
      "position": [
        28.47512622074329,
        4.5,
        -20.303096211635676
      ],
      "rotation": [
        0,
        -1.5707963267948966,
        0
      ],
      "_id": {
        "$oid": "688d9b9540cda3e766bab3b6"
      }
    },
    {
      "decorId": {
        "$oid": "68660edaf079d0ff8d6cc870"
      },
      "placed": false,
      "position": [
        0,
        0,
        0
      ],
      "rotation": [
        0,
        0,
        0
      ],
      "_id": {
        "$oid": "688d9b9740cda3e766bab3ec"
      }
    }
  ]
},
{
  "_id": {
    "$oid": "6867544f9726722b96834d96"
  },
  "userId": {
    "$oid": "6867544f9726722b96834d93"
  },
  "coins": 3400,
  "decorations": [
    {
      "decorId": {
        "$oid": "68660edaf079d0ff8d6cc86d"
      },
      "placed": true,
      "position": [
        20.361896059711235,
        0,
        24.436158236409995
      ],
      "rotation": [
        0,
        0,
        0
      ]
    },
    {
      "decorId": {
        "$oid": "68660edaf079d0ff8d6cc86e"
      },
      "placed": true,
      "position": [
        11.991325521285567,
        0,
        -2.6572974812205885
      ],
      "rotation": [
        0,
        -1.5707963267948966,
        0
      ]
    },
    {
      "decorId": {
        "$oid": "68660edaf079d0ff8d6cc86f"
      },
      "placed": true,
      "position": [
        -19.482668133858482,
        0,
        -11.528593193563701
      ],
      "rotation": [
        0,
        0,
        0
      ]
    },
    {
      "decorId": {
        "$oid": "68660edaf079d0ff8d6cc871"
      },
      "placed": true,
      "position": [
        29.452840200284513,
        15.5,
        -7.715657981499909
      ],
      "rotation": [
        0,
        -1.5707963267948966,
        0
      ]
    },
    {
      "decorId": {
        "$oid": "68660edaf079d0ff8d6cc870"
      },
      "placed": true,
      "position": [
        21.565374682168667,
        0,
        -5.15743973646493
      ],
      "rotation": [
        0,
        -0.9817477042468103,
        0
      ]
    },
    {
      "decorId": {
        "$oid": "68660edaf079d0ff8d6cc872"
      },
      "placed": true,
      "position": [
        -13.850184600304765,
        0,
        17.02568685060757
      ],
      "rotation": [
        0,
        0,
        0
      ]
    }
  ]
},
{
  "_id": {
    "$oid": "688c38e8b6bcb896cdd0b7f5"
  },
  "userId": {
    "$oid": "688c38e8b6bcb896cdd0b7f2"
  },
  "coins": 800,
  "decorations": [
    {
      "decorId": {
        "$oid": "68660edaf079d0ff8d6cc86e"
      },
      "placed": true,
      "position": [
        11.922801261969752,
        0,
        -5.195310457027297
      ],
      "rotation": [
        0,
        -1.5707963267948966,
        0
      ],
      "_id": {
        "$oid": "688c38f6b6bcb896cdd0b812"
      }
    },
    {
      "decorId": {
        "$oid": "68660edaf079d0ff8d6cc872"
      },
      "placed": true,
      "position": [
        8.598513744480222,
        0,
        -7.288828380669791
      ],
      "rotation": [
        0,
        0,
        0
      ],
      "_id": {
        "$oid": "688c38f6b6bcb896cdd0b813"
      }
    },
    {
      "decorId": {
        "$oid": "68660edaf079d0ff8d6cc86f"
      },
      "placed": true,
      "position": [
        13.104777706422844,
        0,
        19.764514286237876
      ],
      "rotation": [
        0,
        -1.5707963267948966,
        0
      ],
      "_id": {
        "$oid": "688c3912b6bcb896cdd0b852"
      }
    }
  ],
  "__v": 0
},
{
  "_id": {
    "$oid": "688c395cb6bcb896cdd0b8c2"
  },
  "userId": {
    "$oid": "688c395cb6bcb896cdd0b8bf"
  },
  "coins": 1200,
  "decorations": [
    {
      "decorId": {
        "$oid": "68660edaf079d0ff8d6cc870"
      },
      "placed": true,
      "position": [
        6.131031569526655,
        0,
        -21.449376895203578
      ],
      "rotation": [
        0,
        0,
        0
      ],
      "_id": {
        "$oid": "688c3969b6bcb896cdd0b909"
      }
    },
    {
      "decorId": {
        "$oid": "68660edaf079d0ff8d6cc871"
      },
      "placed": true,
      "position": [
        29.842111268961872,
        0,
        5.63216717288628
      ],
      "rotation": [
        0,
        -1.5707963267948966,
        0
      ],
      "_id": {
        "$oid": "688c3969b6bcb896cdd0b90a"
      }
    },
    {
      "decorId": {
        "$oid": "68660edaf079d0ff8d6cc86f"
      },
      "placed": true,
      "position": [
        11.667334655063371,
        0,
        20.888689654346187
      ],
      "rotation": [
        0,
        -1.5707963267948966,
        0
      ],
      "_id": {
        "$oid": "688c3969b6bcb896cdd0b90b"
      }
    },
    {
      "decorId": {
        "$oid": "68660edaf079d0ff8d6cc86d"
      },
      "placed": true,
      "position": [
        -5.10811134475702,
        0,
        1.3214135320267495
      ],
      "rotation": [
        0,
        0,
        0
      ],
      "_id": {
        "$oid": "688c3969b6bcb896cdd0b90c"
      }
    }
  ],
  "__v": 0
}]